CHANGES.txt
README.rst
bootstrap.py
buildout.cfg
setup.py
Products/__init__.py
Products.Scrawl.egg-info/PKG-INFO
Products.Scrawl.egg-info/SOURCES.txt
Products.Scrawl.egg-info/SOURCES.txt~
Products.Scrawl.egg-info/dependency_links.txt
Products.Scrawl.egg-info/entry_points.txt
Products.Scrawl.egg-info/namespace_packages.txt
Products.Scrawl.egg-info/not-zip-safe
Products.Scrawl.egg-info/requires.txt
Products.Scrawl.egg-info/top_level.txt
Products/Scrawl/README.txt
Products/Scrawl/__init__.py
Products/Scrawl/config.py
Products/Scrawl/configure.zcml
Products/Scrawl/i18n.py
Products/Scrawl/profiles.zcml
Products/Scrawl/upgrades.py
Products/Scrawl/upgrades.zcml
Products/Scrawl/usei18ndude.sh
Products/Scrawl/version.txt
Products/Scrawl/Extensions/Install.py
Products/Scrawl/Extensions/__init__.py
Products/Scrawl/Extensions/migrate_entries.py
Products/Scrawl/browser/__init__.py
Products/Scrawl/browser/blog.py
Products/Scrawl/browser/blog_view.pt
Products/Scrawl/browser/blog_view_p3.pt
Products/Scrawl/browser/blogentry_icon.png
Products/Scrawl/browser/blogentry_view.pt
Products/Scrawl/browser/blogentry_view_p3.pt
Products/Scrawl/browser/configure.zcml
Products/Scrawl/browser/interfaces.py
Products/Scrawl/locales/scrawl.pot
Products/Scrawl/locales/cs/LC_MESSAGES/scrawl.po
Products/Scrawl/locales/da/LC_MESSAGES/scrawl.po
Products/Scrawl/locales/eo/LC_MESSAGES/scrawl.po
Products/Scrawl/locales/es/LC_MESSAGES/scrawl.po
Products/Scrawl/locales/ja/LC_MESSAGES/scrawl.po
Products/Scrawl/locales/nl/LC_MESSAGES/scrawl.po
Products/Scrawl/locales/pt-br/LC_MESSAGES/scrawl.po
Products/Scrawl/locales/tr/LC_MESSAGES/scrawl.po
Products/Scrawl/profiles/default/browserlayer.xml
Products/Scrawl/profiles/default/factorytool.xml
Products/Scrawl/profiles/default/metadata.xml
Products/Scrawl/profiles/default/types.xml
Products/Scrawl/profiles/default/types/Blog_Entry.xml
Products/Scrawl/profiles/default/types/Topic.xml
Products/Scrawl/profiles/uninstall/factorytool.xml
Products/Scrawl/profiles/uninstall/types.xml
Products/Scrawl/profiles/uninstall/types/Topic.xml
Products/Scrawl/profiles/upgrade_to_20b1/browserlayer.xml
Products/Scrawl/profiles/upgrade_to_20b1/types/Blog_Entry.xml
Products/Scrawl/tests/__init__.py
Products/Scrawl/tests/base.py
Products/Scrawl/tests/browser_add_view_blog.txt
Products/Scrawl/tests/test_functional.py
