Metadata-Version: 1.1
Name: Products.Scrawl
Version: 2.0.2
Summary: Scrawl is a dirt-simple blog product for Plone.
Home-page: http://plone.org/products/scrawl
Author: jbaldivieso
Author-email: jonb@groundwire.org
License: GPL
Keywords: plone blog
Platform: UNKNOWN
Classifier: Programming Language :: Python
Classifier: Framework :: Plone
Classifier: License :: OSI Approved :: GNU General Public License (GPL)
